{
  "metadata": {
    "sourceLanguage": "en",
    "provider": "Oxford University Press",
    "limit": 5000,
    "offset": 0,
    "total": 682
  },
  "results": [
    {
      "word": "abranchiate",
      "id": "abranchiate"
    },
    {
      "word": "abscession",
      "id": "abscession"
    },
    {
      "word": "abstersion",
      "id": "abstersion"
    },
    {
      "word": "acceptilation",
      "id": "acceptilation"
    },
    {
      "word": "accurateness",
      "id": "accurateness"
    },
    {
      "word": "acephal",
      "id": "acephal"
    },
    {
      "word": "achlamydeous",
      "id": "achlamydeous"
    },
    {
      "word": "acidifier",
      "id": "acidifier"
    },
    {
      "word": "acquaintable",
      "id": "acquaintable"
    },
    {
      "word": "acrospore",
      "id": "acrospore"
    },
    {
      "word": "acrostichoid",
      "id": "acrostichoid"
    },
    {
      "word": "acumination",
      "id": "acumination"
    },
    {
      "word": "adamas",
      "id": "adamas"
    },
    {
      "word": "adder's grass",
      "id": "adder%27s_grass"
    },
    {
      "word": "adducer",
      "id": "adducer"
    },
    {
      "word": "adenotomy",
      "id": "adenotomy"
    },
    {
      "word": "adherently",
      "id": "adherently"
    },
    {
      "word": "adiaphoral",
      "id": "adiaphoral"
    },
    {
      "word": "adosculation",
      "id": "adosculation"
    },
    {
      "word": "advergence",
      "id": "advergence"
    },
    {
      "word": "adviceful",
      "id": "adviceful"
    },
    {
      "word": "agamous",
      "id": "agamous"
    },
    {
      "word": "ageusic",
      "id": "ageusic"
    },
    {
      "word": "aghasted",
      "id": "aghasted"
    },
    {
      "word": "aghasting",
      "id": "aghasting"
    },
    {
      "word": "aghastment",
      "id": "aghastment"
    },
    {
      "word": "agitatrix",
      "id": "agitatrix"
    },
    {
      "word": "aimful",
      "id": "aimful"
    },
    {
      "word": "air jacket",
      "id": "air_jacket"
    },
    {
      "word": "akinesis",
      "id": "akinesis"
    },
    {
      "word": "albify",
      "id": "albify"
    },
    {
      "word": "alcyonium",
      "id": "alcyonium"
    },
    {
      "word": "aldehydate",
      "id": "aldehydate"
    },
    {
      "word": "ale tap",
      "id": "ale_tap"
    },
    {
      "word": "aley",
      "id": "aley"
    },
    {
      "word": "alismad",
      "id": "alismad"
    },
    {
      "word": "alkali salt",
      "id": "alkali_salt"
    },
    {
      "word": "alms-deed",
      "id": "alms-deed"
    },
    {
      "word": "almsful",
      "id": "almsful"
    },
    {
      "word": "alms-gift",
      "id": "alms-gift"
    },
    {
      "word": "alure",
      "id": "alure"
    },
    {
      "word": "alutaceous",
      "id": "alutaceous"
    },
    {
      "word": "animated film",
      "id": "animated_film"
    },
    {
      "word": "antarctic sea",
      "id": "antarctic_sea"
    },
    {
      "word": "anthobian",
      "id": "anthobian"
    },
    {
      "word": "antoninianus",
      "id": "antoninianus"
    },
    {
      "word": "anywhither",
      "id": "anywhither"
    },
    {
      "word": "autometry",
      "id": "autometry"
    },
    {
      "word": "automorphic",
      "id": "automorphic"
    },
    {
      "word": "autosite",
      "id": "autosite"
    },
    {
      "word": "baby house",
      "id": "baby_house"
    },
    {
      "word": "balloon bomb",
      "id": "balloon_bomb"
    },
    {
      "word": "bank receipt",
      "id": "bank_receipt"
    },
    {
      "word": "bankside",
      "id": "bankside"
    },
    {
      "word": "black cattle",
      "id": "black_cattle"
    },
    {
      "word": "black maple",
      "id": "black_maple"
    },
    {
      "word": "black vomit",
      "id": "black_vomit"
    },
    {
      "word": "blood rain",
      "id": "blood_rain"
    },
    {
      "word": "bloodwite",
      "id": "bloodwite"
    },
    {
      "word": "blue-aproned",
      "id": "blue-aproned"
    },
    {
      "word": "blue jean",
      "id": "blue_jean"
    },
    {
      "word": "blue star grass",
      "id": "blue_star_grass"
    },
    {
      "word": "body coat",
      "id": "body_coat"
    },
    {
      "word": "book holder",
      "id": "book_holder"
    },
    {
      "word": "bottom rock",
      "id": "bottom_rock"
    },
    {
      "word": "brain trick",
      "id": "brain_trick"
    },
    {
      "word": "callant",
      "id": "callant"
    },
    {
      "word": "canceration",
      "id": "canceration"
    },
    {
      "word": "cape honeysuckle",
      "id": "cape_honeysuckle"
    },
    {
      "word": "carbyl",
      "id": "carbyl"
    },
    {
      "word": "caseate",
      "id": "caseate"
    },
    {
      "word": "centennialize",
      "id": "centennialize"
    },
    {
      "word": "cheese plate",
      "id": "cheese_plate"
    },
    {
      "word": "cheese-toaster",
      "id": "cheese-toaster"
    },
    {
      "word": "chemism",
      "id": "chemism"
    },
    {
      "word": "child-woman",
      "id": "child-woman"
    },
    {
      "word": "church bell",
      "id": "church_bell"
    },
    {
      "word": "churchianity",
      "id": "churchianity"
    },
    {
      "word": "church work",
      "id": "church_work"
    },
    {
      "word": "citharist",
      "id": "citharist"
    },
    {
      "word": "citrated",
      "id": "citrated"
    },
    {
      "word": "classis",
      "id": "classis"
    },
    {
      "word": "cliff rose",
      "id": "cliff_rose"
    },
    {
      "word": "companion cell",
      "id": "companion_cell"
    },
    {
      "word": "contingent fee",
      "id": "contingent_fee"
    },
    {
      "word": "cost drawer",
      "id": "cost_drawer"
    },
    {
      "word": "country dancing",
      "id": "country_dancing"
    },
    {
      "word": "crime rate",
      "id": "crime_rate"
    },
    {
      "word": "cunnigar",
      "id": "cunnigar"
    },
    {
      "word": "cycle-man",
      "id": "cycle-man"
    },
    {
      "word": "cytoid",
      "id": "cytoid"
    },
    {
      "word": "defoedation",
      "id": "defoedation"
    },
    {
      "word": "degree of cold",
      "id": "degree_of_cold"
    },
    {
      "word": "demonstrationer",
      "id": "demonstrationer"
    },
    {
      "word": "demonstrative pronoun",
      "id": "demonstrative_pronoun"
    },
    {
      "word": "dictyoxylon",
      "id": "dictyoxylon"
    },
    {
      "word": "discission",
      "id": "discission"
    },
    {
      "word": "disconsolacy",
      "id": "disconsolacy"
    },
    {
      "word": "discontentful",
      "id": "discontentful"
    },
    {
      "word": "discontenting",
      "id": "discontenting"
    },
    {
      "word": "discourageable",
      "id": "discourageable"
    },
    {
      "word": "dog bramble",
      "id": "dog_bramble"
    },
    {
      "word": "do-naught",
      "id": "do-naught"
    },
    {
      "word": "druggery",
      "id": "druggery"
    },
    {
      "word": "drumble",
      "id": "drumble"
    },
    {
      "word": "ear gristle",
      "id": "ear_gristle"
    },
    {
      "word": "earlid",
      "id": "earlid"
    },
    {
      "word": "electric harpoon",
      "id": "electric_harpoon"
    },
    {
      "word": "electric power",
      "id": "electric_power"
    },
    {
      "word": "electric torch",
      "id": "electric_torch"
    },
    {
      "word": "epistropheus",
      "id": "epistropheus"
    },
    {
      "word": "ethylic",
      "id": "ethylic"
    },
    {
      "word": "ettercap",
      "id": "ettercap"
    },
    {
      "word": "examinate",
      "id": "examinate"
    },
    {
      "word": "face mould",
      "id": "face_mould"
    },
    {
      "word": "factioned",
      "id": "factioned"
    },
    {
      "word": "federator",
      "id": "federator"
    },
    {
      "word": "feelingness",
      "id": "feelingness"
    },
    {
      "word": "field battle",
      "id": "field_battle"
    },
    {
      "word": "field colours",
      "id": "field_colours"
    },
    {
      "word": "field teacher",
      "id": "field_teacher"
    },
    {
      "word": "field word",
      "id": "field_word"
    },
    {
      "word": "fineish",
      "id": "fineish"
    },
    {
      "word": "fire fang",
      "id": "fire_fang"
    },
    {
      "word": "fire-fang",
      "id": "fire-fang"
    },
    {
      "word": "first stomach",
      "id": "first_stomach"
    },
    {
      "word": "fodderer",
      "id": "fodderer"
    },
    {
      "word": "foot piece",
      "id": "foot_piece"
    },
    {
      "word": "fossilia",
      "id": "fossilia"
    },
    {
      "word": "fossil wood",
      "id": "fossil_wood"
    },
    {
      "word": "french broom",
      "id": "french_broom"
    },
    {
      "word": "french walnut",
      "id": "french_walnut"
    },
    {
      "word": "frog dance",
      "id": "frog_dance"
    },
    {
      "word": "frostnip",
      "id": "frostnip"
    },
    {
      "word": "frosty face",
      "id": "frosty_face"
    },
    {
      "word": "full-manned",
      "id": "full-manned"
    },
    {
      "word": "gaminerie",
      "id": "gaminerie"
    },
    {
      "word": "geogeny",
      "id": "geogeny"
    },
    {
      "word": "georgina",
      "id": "georgina"
    },
    {
      "word": "germatic",
      "id": "germatic"
    },
    {
      "word": "going-out",
      "id": "going-out"
    },
    {
      "word": "hackney man",
      "id": "hackney_man"
    },
    {
      "word": "handbreadth",
      "id": "handbreadth"
    },
    {
      "word": "hand vice",
      "id": "hand_vice"
    },
    {
      "word": "hardfish",
      "id": "hardfish"
    },
    {
      "word": "hard soap",
      "id": "hard_soap"
    },
    {
      "word": "heart-aching",
      "id": "heart-aching"
    },
    {
      "word": "helleborism",
      "id": "helleborism"
    },
    {
      "word": "hendecad",
      "id": "hendecad"
    },
    {
      "word": "high blower",
      "id": "high_blower"
    },
    {
      "word": "hog mace",
      "id": "hog_mace"
    },
    {
      "word": "hog meat",
      "id": "hog_meat"
    },
    {
      "word": "honeyfall",
      "id": "honeyfall"
    },
    {
      "word": "honey soap",
      "id": "honey_soap"
    },
    {
      "word": "honorant",
      "id": "honorant"
    },
    {
      "word": "honourer",
      "id": "honourer"
    },
    {
      "word": "hot-mouthed",
      "id": "hot-mouthed"
    },
    {
      "word": "house row",
      "id": "house_row"
    },
    {
      "word": "humorizing",
      "id": "humorizing"
    },
    {
      "word": "identifical",
      "id": "identifical"
    },
    {
      "word": "infectibility",
      "id": "infectibility"
    },
    {
      "word": "informous",
      "id": "informous"
    },
    {
      "word": "internal medicine",
      "id": "internal_medicine"
    },
    {
      "word": "irish diamond",
      "id": "irish_diamond"
    },
    {
      "word": "irish hubbub",
      "id": "irish_hubbub"
    },
    {
      "word": "judiciality",
      "id": "judiciality"
    },
    {
      "word": "key cutter",
      "id": "key_cutter"
    },
    {
      "word": "knaveship",
      "id": "knaveship"
    },
    {
      "word": "labouring time",
      "id": "labouring_time"
    },
    {
      "word": "lavatory stone",
      "id": "lavatory_stone"
    },
    {
      "word": "legumen",
      "id": "legumen"
    },
    {
      "word": "little italy",
      "id": "little_italy"
    },
    {
      "word": "livor",
      "id": "livor"
    },
    {
      "word": "lixivial",
      "id": "lixivial"
    },
    {
      "word": "locrensian",
      "id": "locrensian"
    },
    {
      "word": "longanimity",
      "id": "longanimity"
    },
    {
      "word": "longiroster",
      "id": "longiroster"
    },
    {
      "word": "longirostral",
      "id": "longirostral"
    },
    {
      "word": "longness",
      "id": "longness"
    },
    {
      "word": "long robe",
      "id": "long_robe"
    },
    {
      "word": "long-sided",
      "id": "long-sided"
    },
    {
      "word": "longsomeness",
      "id": "longsomeness"
    },
    {
      "word": "looking on",
      "id": "looking_on"
    },
    {
      "word": "lord-dom",
      "id": "lord-dom"
    },
    {
      "word": "loveday",
      "id": "loveday"
    },
    {
      "word": "love entangled",
      "id": "love_entangled"
    },
    {
      "word": "low wine",
      "id": "low_wine"
    },
    {
      "word": "lptb",
      "id": "lptb"
    },
    {
      "word": "macroseism",
      "id": "macroseism"
    },
    {
      "word": "madwort",
      "id": "madwort"
    },
    {
      "word": "malacia",
      "id": "malacia"
    },
    {
      "word": "mammotrophin",
      "id": "mammotrophin"
    },
    {
      "word": "manna-grass",
      "id": "manna-grass"
    },
    {
      "word": "manoao",
      "id": "manoao"
    },
    {
      "word": "manure distributor",
      "id": "manure_distributor"
    },
    {
      "word": "many a one",
      "id": "many_a_one"
    },
    {
      "word": "maple tree",
      "id": "maple_tree"
    },
    {
      "word": "market street",
      "id": "market_street"
    },
    {
      "word": "marrube",
      "id": "marrube"
    },
    {
      "word": "mass book",
      "id": "mass_book"
    },
    {
      "word": "mastoid bone",
      "id": "mastoid_bone"
    },
    {
      "word": "mean-square error",
      "id": "mean-square_error"
    },
    {
      "word": "measled",
      "id": "measled"
    },
    {
      "word": "mediciner",
      "id": "mediciner"
    },
    {
      "word": "mediety",
      "id": "mediety"
    },
    {
      "word": "medullary ray",
      "id": "medullary_ray"
    },
    {
      "word": "medusa's head",
      "id": "medusa%27s_head"
    },
    {
      "word": "medusean",
      "id": "medusean"
    },
    {
      "word": "megaloscope",
      "id": "megaloscope"
    },
    {
      "word": "melam",
      "id": "melam"
    },
    {
      "word": "melanoblast",
      "id": "melanoblast"
    },
    {
      "word": "melasma",
      "id": "melasma"
    },
    {
      "word": "meliorize",
      "id": "meliorize"
    },
    {
      "word": "memorious",
      "id": "memorious"
    },
    {
      "word": "merchants' accounts",
      "id": "merchants%27_accounts"
    },
    {
      "word": "meristogenetic",
      "id": "meristogenetic"
    },
    {
      "word": "merogamete",
      "id": "merogamete"
    },
    {
      "word": "merogamy",
      "id": "merogamy"
    },
    {
      "word": "meuble",
      "id": "meuble"
    },
    {
      "word": "mexican tiger-flower",
      "id": "mexican_tiger-flower"
    },
    {
      "word": "micarelle",
      "id": "micarelle"
    },
    {
      "word": "microcythaemia",
      "id": "microcythaemia"
    },
    {
      "word": "microseptum",
      "id": "microseptum"
    },
    {
      "word": "microsomia",
      "id": "microsomia"
    },
    {
      "word": "middle latin",
      "id": "middle_latin"
    },
    {
      "word": "mid-finger",
      "id": "mid-finger"
    },
    {
      "word": "midtime",
      "id": "midtime"
    },
    {
      "word": "milken",
      "id": "milken"
    },
    {
      "word": "mill-house",
      "id": "mill-house"
    },
    {
      "word": "mimical",
      "id": "mimical"
    },
    {
      "word": "mincing knife",
      "id": "mincing_knife"
    },
    {
      "word": "mineral coal",
      "id": "mineral_coal"
    },
    {
      "word": "mineral solution",
      "id": "mineral_solution"
    },
    {
      "word": "minework",
      "id": "minework"
    },
    {
      "word": "ministrator",
      "id": "ministrator"
    },
    {
      "word": "miscarrier",
      "id": "miscarrier"
    },
    {
      "word": "miscomputation",
      "id": "miscomputation"
    },
    {
      "word": "misinfer",
      "id": "misinfer"
    },
    {
      "word": "mismade",
      "id": "mismade"
    },
    {
      "word": "mismeaning",
      "id": "mismeaning"
    },
    {
      "word": "misorderly",
      "id": "misorderly"
    },
    {
      "word": "mistuned",
      "id": "mistuned"
    },
    {
      "word": "mithridate mustard",
      "id": "mithridate_mustard"
    },
    {
      "word": "mitosome",
      "id": "mitosome"
    },
    {
      "word": "mixedly",
      "id": "mixedly"
    },
    {
      "word": "mollities",
      "id": "mollities"
    },
    {
      "word": "molybdous",
      "id": "molybdous"
    },
    {
      "word": "moment generating function",
      "id": "moment_generating_function"
    },
    {
      "word": "monastical",
      "id": "monastical"
    },
    {
      "word": "money-hunter",
      "id": "money-hunter"
    },
    {
      "word": "monodont",
      "id": "monodont"
    },
    {
      "word": "monogastric",
      "id": "monogastric"
    },
    {
      "word": "monomyarian",
      "id": "monomyarian"
    },
    {
      "word": "monsterer",
      "id": "monsterer"
    },
    {
      "word": "moonish",
      "id": "moonish"
    },
    {
      "word": "moot hall",
      "id": "moot_hall"
    },
    {
      "word": "mopishness",
      "id": "mopishness"
    },
    {
      "word": "morosity",
      "id": "morosity"
    },
    {
      "word": "morphological axis",
      "id": "morphological_axis"
    },
    {
      "word": "moses boat",
      "id": "moses_boat"
    },
    {
      "word": "mosquito fly",
      "id": "mosquito_fly"
    },
    {
      "word": "moss-crop",
      "id": "moss-crop"
    },
    {
      "word": "moss-rush",
      "id": "moss-rush"
    },
    {
      "word": "mother's pet",
      "id": "mother%27s_pet"
    },
    {
      "word": "mother-of-pearl moth",
      "id": "mother-of-pearl_moth"
    },
    {
      "word": "mouse-eared",
      "id": "mouse-eared"
    },
    {
      "word": "mouse hawk",
      "id": "mouse_hawk"
    },
    {
      "word": "mouth glue",
      "id": "mouth_glue"
    },
    {
      "word": "mucedinous",
      "id": "mucedinous"
    },
    {
      "word": "mud-walled",
      "id": "mud-walled"
    },
    {
      "word": "muguet",
      "id": "muguet"
    },
    {
      "word": "multiplicate",
      "id": "multiplicate"
    },
    {
      "word": "mummied",
      "id": "mummied"
    },
    {
      "word": "muricated",
      "id": "muricated"
    },
    {
      "word": "murmell",
      "id": "murmell"
    },
    {
      "word": "myagrum",
      "id": "myagrum"
    },
    {
      "word": "myoblast",
      "id": "myoblast"
    },
    {
      "word": "myosarcoma",
      "id": "myosarcoma"
    },
    {
      "word": "myrmecobius",
      "id": "myrmecobius"
    },
    {
      "word": "nailwort",
      "id": "nailwort"
    },
    {
      "word": "nar",
      "id": "nar"
    },
    {
      "word": "nassa",
      "id": "nassa"
    },
    {
      "word": "navigatory",
      "id": "navigatory"
    },
    {
      "word": "navy agent",
      "id": "navy_agent"
    },
    {
      "word": "necessary house",
      "id": "necessary_house"
    },
    {
      "word": "need-not",
      "id": "need-not"
    },
    {
      "word": "nenuphar",
      "id": "nenuphar"
    },
    {
      "word": "neocene",
      "id": "neocene"
    },
    {
      "word": "nestler",
      "id": "nestler"
    },
    {
      "word": "neurine",
      "id": "neurine"
    },
    {
      "word": "neuropathist",
      "id": "neuropathist"
    },
    {
      "word": "new-dress",
      "id": "new-dress"
    },
    {
      "word": "newlings",
      "id": "newlings"
    },
    {
      "word": "news writer",
      "id": "news_writer"
    },
    {
      "word": "night-gear",
      "id": "night-gear"
    },
    {
      "word": "night trader",
      "id": "night_trader"
    },
    {
      "word": "night-watching",
      "id": "night-watching"
    },
    {
      "word": "nitrometer",
      "id": "nitrometer"
    },
    {
      "word": "nociferous",
      "id": "nociferous"
    },
    {
      "word": "nomology",
      "id": "nomology"
    },
    {
      "word": "non-ability",
      "id": "non-ability"
    },
    {
      "word": "non-intelligent",
      "id": "non-intelligent"
    },
    {
      "word": "non-swearing",
      "id": "non-swearing"
    },
    {
      "word": "november moth",
      "id": "november_moth"
    },
    {
      "word": "nucule",
      "id": "nucule"
    },
    {
      "word": "nymphon",
      "id": "nymphon"
    },
    {
      "word": "oaken pin",
      "id": "oaken_pin"
    },
    {
      "word": "oak pest",
      "id": "oak_pest"
    },
    {
      "word": "oat-seed bird",
      "id": "oat-seed_bird"
    },
    {
      "word": "obnoxiety",
      "id": "obnoxiety"
    },
    {
      "word": "octopartite",
      "id": "octopartite"
    },
    {
      "word": "oculate",
      "id": "oculate"
    },
    {
      "word": "oidiomycosis",
      "id": "oidiomycosis"
    },
    {
      "word": "oil bag",
      "id": "oil_bag"
    },
    {
      "word": "oil state",
      "id": "oil_state"
    },
    {
      "word": "olein",
      "id": "olein"
    },
    {
      "word": "omphalomancy",
      "id": "omphalomancy"
    },
    {
      "word": "ondatra",
      "id": "ondatra"
    },
    {
      "word": "onfall",
      "id": "onfall"
    },
    {
      "word": "oniscus",
      "id": "oniscus"
    },
    {
      "word": "onychia",
      "id": "onychia"
    },
    {
      "word": "opal plate",
      "id": "opal_plate"
    },
    {
      "word": "ophiophagus",
      "id": "ophiophagus"
    },
    {
      "word": "ophiura",
      "id": "ophiura"
    },
    {
      "word": "opinionately",
      "id": "opinionately"
    },
    {
      "word": "optic ganglion",
      "id": "optic_ganglion"
    },
    {
      "word": "orange butter",
      "id": "orange_butter"
    },
    {
      "word": "orange mint",
      "id": "orange_mint"
    },
    {
      "word": "orchitic",
      "id": "orchitic"
    },
    {
      "word": "origan",
      "id": "origan"
    },
    {
      "word": "orthopnoea",
      "id": "orthopnoea"
    },
    {
      "word": "os externum",
      "id": "os_externum"
    },
    {
      "word": "os internum",
      "id": "os_internum"
    },
    {
      "word": "osphresiology",
      "id": "osphresiology"
    },
    {
      "word": "outborn",
      "id": "outborn"
    },
    {
      "word": "overabound",
      "id": "overabound"
    },
    {
      "word": "overcharger",
      "id": "overcharger"
    },
    {
      "word": "over-close",
      "id": "over-close"
    },
    {
      "word": "overflowingly",
      "id": "overflowingly"
    },
    {
      "word": "overflowingness",
      "id": "overflowingness"
    },
    {
      "word": "overlargely",
      "id": "overlargely"
    },
    {
      "word": "overpester",
      "id": "overpester"
    },
    {
      "word": "oversalt",
      "id": "oversalt"
    },
    {
      "word": "over-vain",
      "id": "over-vain"
    },
    {
      "word": "paganistic",
      "id": "paganistic"
    },
    {
      "word": "painting cloth",
      "id": "painting_cloth"
    },
    {
      "word": "palace-like",
      "id": "palace-like"
    },
    {
      "word": "palaestric",
      "id": "palaestric"
    },
    {
      "word": "pallet spring",
      "id": "pallet_spring"
    },
    {
      "word": "palma christi",
      "id": "palma_christi"
    },
    {
      "word": "palm-nut tree",
      "id": "palm-nut_tree"
    },
    {
      "word": "paludament",
      "id": "paludament"
    },
    {
      "word": "pank",
      "id": "pank"
    },
    {
      "word": "pan pudding",
      "id": "pan_pudding"
    },
    {
      "word": "pansperm",
      "id": "pansperm"
    },
    {
      "word": "panter",
      "id": "panter"
    },
    {
      "word": "pantophobia",
      "id": "pantophobia"
    },
    {
      "word": "pantopragmatic",
      "id": "pantopragmatic"
    },
    {
      "word": "panyarring",
      "id": "panyarring"
    },
    {
      "word": "papistic",
      "id": "papistic"
    },
    {
      "word": "paracusis",
      "id": "paracusis"
    },
    {
      "word": "paradisaeine",
      "id": "paradisaeine"
    },
    {
      "word": "pargeter",
      "id": "pargeter"
    },
    {
      "word": "paris doll",
      "id": "paris_doll"
    },
    {
      "word": "park leaves",
      "id": "park_leaves"
    },
    {
      "word": "parlatory",
      "id": "parlatory"
    },
    {
      "word": "parnel",
      "id": "parnel"
    },
    {
      "word": "parrock",
      "id": "parrock"
    },
    {
      "word": "parsley water dropwort",
      "id": "parsley_water_dropwort"
    },
    {
      "word": "parson-and-clerk",
      "id": "parson-and-clerk"
    },
    {
      "word": "parthenium",
      "id": "parthenium"
    },
    {
      "word": "passport letter",
      "id": "passport_letter"
    },
    {
      "word": "patrimony of st peter",
      "id": "patrimony_of_st_peter"
    },
    {
      "word": "pausation",
      "id": "pausation"
    },
    {
      "word": "peasemeal",
      "id": "peasemeal"
    },
    {
      "word": "pectorally",
      "id": "pectorally"
    },
    {
      "word": "pendently",
      "id": "pendently"
    },
    {
      "word": "penniless bench",
      "id": "penniless_bench"
    },
    {
      "word": "pennoncel",
      "id": "pennoncel"
    },
    {
      "word": "pennyboy",
      "id": "pennyboy"
    },
    {
      "word": "pension house",
      "id": "pension_house"
    },
    {
      "word": "pentandrous",
      "id": "pentandrous"
    },
    {
      "word": "perennibranchiate",
      "id": "perennibranchiate"
    },
    {
      "word": "perforate st john's-wort",
      "id": "perforate_st_john%27s-wort"
    },
    {
      "word": "perineuritis",
      "id": "perineuritis"
    },
    {
      "word": "periodontium",
      "id": "periodontium"
    },
    {
      "word": "periost",
      "id": "periost"
    },
    {
      "word": "periplast",
      "id": "periplast"
    },
    {
      "word": "perispore",
      "id": "perispore"
    },
    {
      "word": "perorator",
      "id": "perorator"
    },
    {
      "word": "personed",
      "id": "personed"
    },
    {
      "word": "perspicience",
      "id": "perspicience"
    },
    {
      "word": "pest man",
      "id": "pest_man"
    },
    {
      "word": "petrarchize",
      "id": "petrarchize"
    },
    {
      "word": "petrific",
      "id": "petrific"
    },
    {
      "word": "petticoat maker",
      "id": "petticoat_maker"
    },
    {
      "word": "pettitoe",
      "id": "pettitoe"
    },
    {
      "word": "phenylamide",
      "id": "phenylamide"
    },
    {
      "word": "philanthropinist",
      "id": "philanthropinist"
    },
    {
      "word": "philomath",
      "id": "philomath"
    },
    {
      "word": "philomathy",
      "id": "philomathy"
    },
    {
      "word": "photian",
      "id": "photian"
    },
    {
      "word": "photics",
      "id": "photics"
    },
    {
      "word": "phototype",
      "id": "phototype"
    },
    {
      "word": "phyllophagan",
      "id": "phyllophagan"
    },
    {
      "word": "physiognomics",
      "id": "physiognomics"
    },
    {
      "word": "physis",
      "id": "physis"
    },
    {
      "word": "picine",
      "id": "picine"
    },
    {
      "word": "pickmaw",
      "id": "pickmaw"
    },
    {
      "word": "picnickian",
      "id": "picnickian"
    },
    {
      "word": "pig's wool",
      "id": "pig%27s_wool"
    },
    {
      "word": "pig boy",
      "id": "pig_boy"
    },
    {
      "word": "pike-headed",
      "id": "pike-headed"
    },
    {
      "word": "pioneer corps",
      "id": "pioneer_corps"
    },
    {
      "word": "piratize",
      "id": "piratize"
    },
    {
      "word": "placeholding",
      "id": "placeholding"
    },
    {
      "word": "plaidoyer",
      "id": "plaidoyer"
    },
    {
      "word": "plain-headed",
      "id": "plain-headed"
    },
    {
      "word": "plaintful",
      "id": "plaintful"
    },
    {
      "word": "plancher",
      "id": "plancher"
    },
    {
      "word": "plantage",
      "id": "plantage"
    },
    {
      "word": "plant-animal",
      "id": "plant-animal"
    },
    {
      "word": "platform party",
      "id": "platform_party"
    },
    {
      "word": "play-day",
      "id": "play-day"
    },
    {
      "word": "pleaful",
      "id": "pleaful"
    },
    {
      "word": "pleasable",
      "id": "pleasable"
    },
    {
      "word": "pleuroconch",
      "id": "pleuroconch"
    },
    {
      "word": "plicature",
      "id": "plicature"
    },
    {
      "word": "pluff",
      "id": "pluff"
    },
    {
      "word": "pneumato-chemical",
      "id": "pneumato-chemical"
    },
    {
      "word": "pocket protector",
      "id": "pocket_protector"
    },
    {
      "word": "podestate",
      "id": "podestate"
    },
    {
      "word": "podology",
      "id": "podology"
    },
    {
      "word": "podoscaph",
      "id": "podoscaph"
    },
    {
      "word": "polemy",
      "id": "polemy"
    },
    {
      "word": "policlinic",
      "id": "policlinic"
    },
    {
      "word": "polissoir",
      "id": "polissoir"
    },
    {
      "word": "polyadelphous",
      "id": "polyadelphous"
    },
    {
      "word": "polybasic",
      "id": "polybasic"
    },
    {
      "word": "polycystine",
      "id": "polycystine"
    },
    {
      "word": "polylemma",
      "id": "polylemma"
    },
    {
      "word": "polymyarian",
      "id": "polymyarian"
    },
    {
      "word": "polyodont",
      "id": "polyodont"
    },
    {
      "word": "polyparium",
      "id": "polyparium"
    },
    {
      "word": "polypetalous",
      "id": "polypetalous"
    },
    {
      "word": "polypifer",
      "id": "polypifer"
    },
    {
      "word": "polyspast",
      "id": "polyspast"
    },
    {
      "word": "pompatic",
      "id": "pompatic"
    },
    {
      "word": "poncho dress",
      "id": "poncho_dress"
    },
    {
      "word": "ponent",
      "id": "ponent"
    },
    {
      "word": "poodle fashion",
      "id": "poodle_fashion"
    },
    {
      "word": "popehood",
      "id": "popehood"
    },
    {
      "word": "porphyrio",
      "id": "porphyrio"
    },
    {
      "word": "posterotemporal",
      "id": "posterotemporal"
    },
    {
      "word": "postpalatal",
      "id": "postpalatal"
    },
    {
      "word": "post-runner",
      "id": "post-runner"
    },
    {
      "word": "postsynapsis",
      "id": "postsynapsis"
    },
    {
      "word": "pot fisherman",
      "id": "pot_fisherman"
    },
    {
      "word": "poting",
      "id": "poting"
    },
    {
      "word": "potomania",
      "id": "potomania"
    },
    {
      "word": "pounds worth",
      "id": "pounds_worth"
    },
    {
      "word": "powderous",
      "id": "powderous"
    },
    {
      "word": "power tool",
      "id": "power_tool"
    },
    {
      "word": "practicant",
      "id": "practicant"
    },
    {
      "word": "praecordia",
      "id": "praecordia"
    },
    {
      "word": "pragmaticalness",
      "id": "pragmaticalness"
    },
    {
      "word": "pre-admit",
      "id": "pre-admit"
    },
    {
      "word": "pregnation",
      "id": "pregnation"
    },
    {
      "word": "prehalter",
      "id": "prehalter"
    },
    {
      "word": "prescriptionary",
      "id": "prescriptionary"
    },
    {
      "word": "pretenceless",
      "id": "pretenceless"
    },
    {
      "word": "prevailable",
      "id": "prevailable"
    },
    {
      "word": "prevailency",
      "id": "prevailency"
    },
    {
      "word": "priapist",
      "id": "priapist"
    },
    {
      "word": "priapize",
      "id": "priapize"
    },
    {
      "word": "primicery",
      "id": "primicery"
    },
    {
      "word": "primrose peerless",
      "id": "primrose_peerless"
    },
    {
      "word": "princewood",
      "id": "princewood"
    },
    {
      "word": "prison-free",
      "id": "prison-free"
    },
    {
      "word": "pritch",
      "id": "pritch"
    },
    {
      "word": "private mass",
      "id": "private_mass"
    },
    {
      "word": "privateness",
      "id": "privateness"
    },
    {
      "word": "procession day",
      "id": "procession_day"
    },
    {
      "word": "proke",
      "id": "proke"
    },
    {
      "word": "prolificate",
      "id": "prolificate"
    },
    {
      "word": "promerops",
      "id": "promerops"
    },
    {
      "word": "pro-parent",
      "id": "pro-parent"
    },
    {
      "word": "propargylate",
      "id": "propargylate"
    },
    {
      "word": "propargylic ether",
      "id": "propargylic_ether"
    },
    {
      "word": "propine",
      "id": "propine"
    },
    {
      "word": "proptosed",
      "id": "proptosed"
    },
    {
      "word": "proto-organism",
      "id": "proto-organism"
    },
    {
      "word": "protovertebra",
      "id": "protovertebra"
    },
    {
      "word": "province line",
      "id": "province_line"
    },
    {
      "word": "psammite",
      "id": "psammite"
    },
    {
      "word": "pseudolabium",
      "id": "pseudolabium"
    },
    {
      "word": "pseudoparasite",
      "id": "pseudoparasite"
    },
    {
      "word": "pseudotetramerous",
      "id": "pseudotetramerous"
    },
    {
      "word": "psychogony",
      "id": "psychogony"
    },
    {
      "word": "pteridoid",
      "id": "pteridoid"
    },
    {
      "word": "pteris",
      "id": "pteris"
    },
    {
      "word": "pterygoid bone",
      "id": "pterygoid_bone"
    },
    {
      "word": "public offer",
      "id": "public_offer"
    },
    {
      "word": "public weal",
      "id": "public_weal"
    },
    {
      "word": "pullishee",
      "id": "pullishee"
    },
    {
      "word": "puncturation",
      "id": "puncturation"
    },
    {
      "word": "purple lily",
      "id": "purple_lily"
    },
    {
      "word": "purpurine",
      "id": "purpurine"
    },
    {
      "word": "purse-bearing",
      "id": "purse-bearing"
    },
    {
      "word": "purse-emptier",
      "id": "purse-emptier"
    },
    {
      "word": "pyromucic",
      "id": "pyromucic"
    },
    {
      "word": "quadrigamist",
      "id": "quadrigamist"
    },
    {
      "word": "quadrilogue",
      "id": "quadrilogue"
    },
    {
      "word": "quarter-board",
      "id": "quarter-board"
    },
    {
      "word": "quarterdecker",
      "id": "quarterdecker"
    },
    {
      "word": "quercine",
      "id": "quercine"
    },
    {
      "word": "quinovic acid",
      "id": "quinovic_acid"
    },
    {
      "word": "quinquefoliated",
      "id": "quinquefoliated"
    },
    {
      "word": "quintary",
      "id": "quintary"
    },
    {
      "word": "qui tam",
      "id": "qui_tam"
    },
    {
      "word": "raffler",
      "id": "raffler"
    },
    {
      "word": "raftering",
      "id": "raftering"
    },
    {
      "word": "rag merchant",
      "id": "rag_merchant"
    },
    {
      "word": "rag wick",
      "id": "rag_wick"
    },
    {
      "word": "rain-bath",
      "id": "rain-bath"
    },
    {
      "word": "rain cuckoo",
      "id": "rain_cuckoo"
    },
    {
      "word": "ramulous",
      "id": "ramulous"
    },
    {
      "word": "ranine",
      "id": "ranine"
    },
    {
      "word": "raphanus",
      "id": "raphanus"
    },
    {
      "word": "rasorial",
      "id": "rasorial"
    },
    {
      "word": "raw spun",
      "id": "raw_spun"
    },
    {
      "word": "reaccommodate",
      "id": "reaccommodate"
    },
    {
      "word": "reaccrue",
      "id": "reaccrue"
    },
    {
      "word": "recordative",
      "id": "recordative"
    },
    {
      "word": "recumb",
      "id": "recumb"
    },
    {
      "word": "redbeard",
      "id": "redbeard"
    },
    {
      "word": "redesman",
      "id": "redesman"
    },
    {
      "word": "redfin shiner",
      "id": "redfin_shiner"
    },
    {
      "word": "red gown",
      "id": "red_gown"
    },
    {
      "word": "red lamp",
      "id": "red_lamp"
    },
    {
      "word": "red robin",
      "id": "red_robin"
    },
    {
      "word": "red varnish",
      "id": "red_varnish"
    },
    {
      "word": "reed-grass",
      "id": "reed-grass"
    },
    {
      "word": "re-embody",
      "id": "re-embody"
    },
    {
      "word": "re-entertain",
      "id": "re-entertain"
    },
    {
      "word": "refashionment",
      "id": "refashionment"
    },
    {
      "word": "refetch",
      "id": "refetch"
    },
    {
      "word": "refracter",
      "id": "refracter"
    },
    {
      "word": "refraid",
      "id": "refraid"
    },
    {
      "word": "refreshful",
      "id": "refreshful"
    },
    {
      "word": "refrigerium",
      "id": "refrigerium"
    },
    {
      "word": "refuged",
      "id": "refuged"
    },
    {
      "word": "regratify",
      "id": "regratify"
    },
    {
      "word": "rehonour",
      "id": "rehonour"
    },
    {
      "word": "rehumble",
      "id": "rehumble"
    },
    {
      "word": "rejuvenesce",
      "id": "rejuvenesce"
    },
    {
      "word": "repealment",
      "id": "repealment"
    },
    {
      "word": "repleve",
      "id": "repleve"
    },
    {
      "word": "representator",
      "id": "representator"
    },
    {
      "word": "re-say",
      "id": "re-say"
    },
    {
      "word": "respeak",
      "id": "respeak"
    },
    {
      "word": "restigmatize",
      "id": "restigmatize"
    },
    {
      "word": "retinaculum",
      "id": "retinaculum"
    },
    {
      "word": "return wave",
      "id": "return_wave"
    },
    {
      "word": "revengement",
      "id": "revengement"
    },
    {
      "word": "revestry",
      "id": "revestry"
    },
    {
      "word": "rewend",
      "id": "rewend"
    },
    {
      "word": "rheic acid",
      "id": "rheic_acid"
    },
    {
      "word": "rhetoricalness",
      "id": "rhetoricalness"
    },
    {
      "word": "rheumatizing",
      "id": "rheumatizing"
    },
    {
      "word": "rhizodont",
      "id": "rhizodont"
    },
    {
      "word": "rhizomorphous",
      "id": "rhizomorphous"
    },
    {
      "word": "rib stocking",
      "id": "rib_stocking"
    },
    {
      "word": "rich man",
      "id": "rich_man"
    },
    {
      "word": "ridge bone",
      "id": "ridge_bone"
    },
    {
      "word": "rigbone",
      "id": "rigbone"
    },
    {
      "word": "roadsman",
      "id": "roadsman"
    },
    {
      "word": "robur carolinum",
      "id": "robur_carolinum"
    },
    {
      "word": "rock mine",
      "id": "rock_mine"
    },
    {
      "word": "rock mouse",
      "id": "rock_mouse"
    },
    {
      "word": "rock rat",
      "id": "rock_rat"
    },
    {
      "word": "rock sandpiper",
      "id": "rock_sandpiper"
    },
    {
      "word": "rocky mountain feathers",
      "id": "rocky_mountain_feathers"
    },
    {
      "word": "romanish",
      "id": "romanish"
    },
    {
      "word": "rome-runner",
      "id": "rome-runner"
    },
    {
      "word": "roselet",
      "id": "roselet"
    },
    {
      "word": "rotten-rich",
      "id": "rotten-rich"
    },
    {
      "word": "rough spleenwort",
      "id": "rough_spleenwort"
    },
    {
      "word": "round o",
      "id": "round_o"
    },
    {
      "word": "roundure",
      "id": "roundure"
    },
    {
      "word": "rubrify",
      "id": "rubrify"
    },
    {
      "word": "rupicapra",
      "id": "rupicapra"
    },
    {
      "word": "rutilite",
      "id": "rutilite"
    },
    {
      "word": "salinate",
      "id": "salinate"
    },
    {
      "word": "saturnight",
      "id": "saturnight"
    },
    {
      "word": "scene work",
      "id": "scene_work"
    },
    {
      "word": "school method",
      "id": "school_method"
    },
    {
      "word": "sciaena",
      "id": "sciaena"
    },
    {
      "word": "scimitared",
      "id": "scimitared"
    },
    {
      "word": "she-friend",
      "id": "she-friend"
    },
    {
      "word": "sidely",
      "id": "sidely"
    },
    {
      "word": "skin-dried",
      "id": "skin-dried"
    },
    {
      "word": "softening machine",
      "id": "softening_machine"
    },
    {
      "word": "sporting man",
      "id": "sporting_man"
    },
    {
      "word": "spotted hog deer",
      "id": "spotted_hog_deer"
    },
    {
      "word": "spotted seal",
      "id": "spotted_seal"
    },
    {
      "word": "spout mouth",
      "id": "spout_mouth"
    },
    {
      "word": "state prison",
      "id": "state_prison"
    },
    {
      "word": "stone cress",
      "id": "stone_cress"
    },
    {
      "word": "street cleaning",
      "id": "street_cleaning"
    },
    {
      "word": "strengthful",
      "id": "strengthful"
    },
    {
      "word": "structurer",
      "id": "structurer"
    },
    {
      "word": "studier",
      "id": "studier"
    },
    {
      "word": "subcrureus",
      "id": "subcrureus"
    },
    {
      "word": "sub-elementary",
      "id": "sub-elementary"
    },
    {
      "word": "subplant",
      "id": "subplant"
    },
    {
      "word": "subsidation",
      "id": "subsidation"
    },
    {
      "word": "subsidium",
      "id": "subsidium"
    },
    {
      "word": "subvassalage",
      "id": "subvassalage"
    },
    {
      "word": "subventive",
      "id": "subventive"
    },
    {
      "word": "supersault",
      "id": "supersault"
    },
    {
      "word": "supposal",
      "id": "supposal"
    },
    {
      "word": "table vessel",
      "id": "table_vessel"
    },
    {
      "word": "take-in",
      "id": "take-in"
    },
    {
      "word": "telegraphone",
      "id": "telegraphone"
    },
    {
      "word": "telephonable",
      "id": "telephonable"
    },
    {
      "word": "telephone record",
      "id": "telephone_record"
    },
    {
      "word": "telephonetics",
      "id": "telephonetics"
    },
    {
      "word": "toilet chamber",
      "id": "toilet_chamber"
    },
    {
      "word": "toilet cloth",
      "id": "toilet_cloth"
    },
    {
      "word": "to one's (also the) finger (also fingers') ends",
      "id": "to_one%27s_%28also_the%29_finger_%28also_fingers%27%29_ends"
    },
    {
      "word": "town child",
      "id": "town_child"
    },
    {
      "word": "tradeful",
      "id": "tradeful"
    },
    {
      "word": "traductionist",
      "id": "traductionist"
    },
    {
      "word": "trusteed",
      "id": "trusteed"
    },
    {
      "word": "tuberculoma",
      "id": "tuberculoma"
    },
    {
      "word": "unmanhood",
      "id": "unmanhood"
    },
    {
      "word": "unmartyred",
      "id": "unmartyred"
    },
    {
      "word": "unmeek",
      "id": "unmeek"
    },
    {
      "word": "unmeekly",
      "id": "unmeekly"
    },
    {
      "word": "unmeekness",
      "id": "unmeekness"
    },
    {
      "word": "unmerry",
      "id": "unmerry"
    },
    {
      "word": "unpensioned",
      "id": "unpensioned"
    },
    {
      "word": "unperformance",
      "id": "unperformance"
    },
    {
      "word": "unperplexed",
      "id": "unperplexed"
    },
    {
      "word": "unpertinent",
      "id": "unpertinent"
    },
    {
      "word": "unpestered",
      "id": "unpestered"
    },
    {
      "word": "unpieced",
      "id": "unpieced"
    },
    {
      "word": "unprejudged",
      "id": "unprejudged"
    },
    {
      "word": "unproper",
      "id": "unproper"
    },
    {
      "word": "unproperly",
      "id": "unproperly"
    },
    {
      "word": "unrailed",
      "id": "unrailed"
    },
    {
      "word": "unreproved",
      "id": "unreproved"
    },
    {
      "word": "unrich",
      "id": "unrich"
    },
    {
      "word": "unrule",
      "id": "unrule"
    },
    {
      "word": "variolate",
      "id": "variolate"
    },
    {
      "word": "variolated",
      "id": "variolated"
    },
    {
      "word": "variolation",
      "id": "variolation"
    },
    {
      "word": "vegetable gold",
      "id": "vegetable_gold"
    },
    {
      "word": "vegeto-mineral",
      "id": "vegeto-mineral"
    },
    {
      "word": "want-creating",
      "id": "want-creating"
    },
    {
      "word": "water cask",
      "id": "water_cask"
    },
    {
      "word": "watersail",
      "id": "watersail"
    },
    {
      "word": "waterwort",
      "id": "waterwort"
    },
    {
      "word": "well-decked",
      "id": "well-decked"
    },
    {
      "word": "well-improved",
      "id": "well-improved"
    },
    {
      "word": "well-meaner",
      "id": "well-meaner"
    },
    {
      "word": "well-modelled",
      "id": "well-modelled"
    },
    {
      "word": "well-named",
      "id": "well-named"
    },
    {
      "word": "well-natured",
      "id": "well-natured"
    },
    {
      "word": "well-recorded",
      "id": "well-recorded"
    },
    {
      "word": "well to pass",
      "id": "well_to_pass"
    },
    {
      "word": "well-wish",
      "id": "well-wish"
    },
    {
      "word": "white dogwood",
      "id": "white_dogwood"
    },
    {
      "word": "white-leaved",
      "id": "white-leaved"
    },
    {
      "word": "white rot",
      "id": "white_rot"
    },
    {
      "word": "wirework",
      "id": "wirework"
    },
    {
      "word": "working life",
      "id": "working_life"
    },
    {
      "word": "working place",
      "id": "working_place"
    },
    {
      "word": "world-wise",
      "id": "world-wise"
    },
    {
      "word": "year by year",
      "id": "year_by_year"
    },
    {
      "word": "year-day",
      "id": "year-day"
    }
  ]
}